tests/__init__.py
tests/test_constants.py
tests/test_data.py
tests/test_latex.py
tests/test_symbolf.py
tests/test_uncertainty.py
ueca/__init__.py
ueca/constants.py
ueca/data.py
ueca/latex.py
ueca/symbolf.py
ueca/uncertainty.py
ueca-0.1.0.dist-info/LICENSE
ueca-0.1.0.dist-info/METADATA
ueca-0.1.0.dist-info/WHEEL
ueca-0.1.0.dist-info/top_level.txt
ueca-0.1.0.dist-info/RECORD
