Metadata-Version: 2.1
Name: ueca
Version: 0.1.0
Summary: 基礎化学実験AのためのPythonライブラリ
Home-page: https://github.com/A03ki/ueca
Author: puman03(Aki)
Author-email: a03ki04@gmail.com
License: MIT License
Keywords: UEC
Platform: UNKNOWN
Classifier: License :: OSI Approved :: MIT License
Classifier: Programming Language :: Python :: 3.6
Classifier: Programming Language :: Python :: 3.7
Classifier: Programming Language :: Python :: 3.8
Requires-Python: >=3.6, <3.9
Requires-Dist: numpy
Requires-Dist: pint
Requires-Dist: scipy
Requires-Dist: sympy
Requires-Dist: uncertainties
Provides-Extra: tests
Requires-Dist: pytest ; extra == 'tests'
